pae/redis/__init__.py
pae/redis/checks.py
pae/redis/default_settings.py
pae/redis/factory.py
pyapp_ext/redis/__init__.py
pyapp_ext/redis/checks.py
pyapp_ext/redis/default_settings.py
pyapp_ext/redis/factory.py
pyApp_Redis-1.0.dist-info/LICENSE
pyApp_Redis-1.0.dist-info/METADATA
pyApp_Redis-1.0.dist-info/WHEEL
pyApp_Redis-1.0.dist-info/entry_points.txt
pyApp_Redis-1.0.dist-info/top_level.txt
pyApp_Redis-1.0.dist-info/RECORD
